Classfile /Users/luisfalcao/Library/CloudStorage/OneDrive-InstitutoSuperiordeEngenhariadeLisboa/ISEL/Disciplinas/2024_2025/2024-2025VerLAE/Repositories/2025-lae-41n-LF/Lesson16/build/classes/java/test/isel/lae/li41n/mapper/MapperDynCourseExtToCourseInternalJava.class
  Last modified Apr 14, 2025; size 1262 bytes
  SHA-256 checksum b34e67a367949e7336d521da3a5e95663a540ae878ea77c69fcbb878b0982e02
  Compiled from "MapperDynCourseExtToCourseInternalJava.java"
public class isel.lae.li41n.mapper.mappers.MapperDynCourseExtToCourseInternalJava extends java.lang.Object implements isel.lae.li41n.mapper.Mapper<isel.lae.li41n.mapper.CourseExt, isel.lae.li41n.mapper.CourseInternal>
  minor version: 0
  major version: 66
  flags: (0x0021) ACC_PUBLIC, ACC_SUPER
  this_class: #26                         // isel/lae/li41n/mapper/MapperDynCourseExtToCourseInternalJava
  super_class: #2                         // java/lang/Object
  interfaces: 1, fields: 0, methods: 3, attributes: 2
Constant pool:
   #1 = Methodref          #2.#3          // java/lang/Object."<init>":()V
   #2 = Class              #4             // java/lang/Object
   #3 = NameAndType        #5:#6          // "<init>":()V
   #4 = Utf8               java/lang/Object
   #5 = Utf8               <init>
   #6 = Utf8               ()V
   #7 = Methodref          #8.#9          // isel/lae/li41n/mapper/CourseExt.getName:()Ljava/lang/String;
   #8 = Class              #10            // isel/lae/li41n/mapper/CourseExt
   #9 = NameAndType        #11:#12        // getName:()Ljava/lang/String;
  #10 = Utf8               isel/lae/li41n/mapper/CourseExt
  #11 = Utf8               getName
  #12 = Utf8               ()Ljava/lang/String;
  #13 = Methodref          #8.#14         // isel/lae/li41n/mapper/CourseExt.getSemester:()I
  #14 = NameAndType        #15:#16        // getSemester:()I
  #15 = Utf8               getSemester
  #16 = Utf8               ()I
  #17 = Methodref          #8.#18         // isel/lae/li41n/mapper/CourseExt.getProgramme:()Ljava/lang/String;
  #18 = NameAndType        #19:#12        // getProgramme:()Ljava/lang/String;
  #19 = Utf8               getProgramme
  #20 = Class              #21            // isel/lae/li41n/mapper/CourseInternal
  #21 = Utf8               isel/lae/li41n/mapper/CourseInternal
  #22 = Methodref          #20.#23        // isel/lae/li41n/mapper/CourseInternal."<init>":(Ljava/lang/String;ILjava/lang/String;I)V
  #23 = NameAndType        #5:#24         // "<init>":(Ljava/lang/String;ILjava/lang/String;I)V
  #24 = Utf8               (Ljava/lang/String;ILjava/lang/String;I)V
  #25 = Methodref          #26.#27        // isel/lae/li41n/mapper/MapperDynCourseExtToCourseInternalJava.mapTo:(Lisel/lae/li41n/mapper/CourseExt;)Lisel/lae/li41n/mapper/CourseInternal;
  #26 = Class              #28            // isel/lae/li41n/mapper/MapperDynCourseExtToCourseInternalJava
  #27 = NameAndType        #29:#30        // mapTo:(Lisel/lae/li41n/mapper/CourseExt;)Lisel/lae/li41n/mapper/CourseInternal;
  #28 = Utf8               isel/lae/li41n/mapper/MapperDynCourseExtToCourseInternalJava
  #29 = Utf8               mapTo
  #30 = Utf8               (Lisel/lae/li41n/mapper/CourseExt;)Lisel/lae/li41n/mapper/CourseInternal;
  #31 = Class              #32            // isel/lae/li41n/mapper/Mapper
  #32 = Utf8               isel/lae/li41n/mapper/Mapper
  #33 = Utf8               Code
  #34 = Utf8               LineNumberTable
  #35 = Utf8               LocalVariableTable
  #36 = Utf8               this
  #37 = Utf8               Lisel/lae/li41n/mapper/MapperDynCourseExtToCourseInternalJava;
  #38 = Utf8               src
  #39 = Utf8               Lisel/lae/li41n/mapper/CourseExt;
  #40 = Utf8               name
  #41 = Utf8               Ljava/lang/String;
  #42 = Utf8               semester
  #43 = Utf8               I
  #44 = Utf8               programme
  #45 = Utf8               (Ljava/lang/Object;)Ljava/lang/Object;
  #46 = Utf8               MethodParameters
  #47 = Utf8               Signature
  #48 = Utf8               Ljava/lang/Object;Lisel/lae/li41n/mapper/Mapper<Lisel/lae/li41n/mapper/CourseExt;Lisel/lae/li41n/mapper/CourseInternal;>;
  #49 = Utf8               SourceFile
  #50 = Utf8               MapperDynCourseExtToCourseInternalJava.java
{
  public isel.lae.li41n.mapper.mappers.MapperDynCourseExtToCourseInternalJava();
    descriptor: ()V
    flags: (0x0001) ACC_PUBLIC
    Code:
      stack=1, locals=1, args_size=1
         0: aload_0
         1: invokespecial #1                  // Method java/lang/Object."<init>":()V
         4: return
      LineNumberTable:
        line 5: 0
        line 6: 4
      LocalVariableTable:
        Start  Length  Slot  Name   Signature
            0       5     0  this   Lisel/lae/li41n/mapper/MapperDynCourseExtToCourseInternalJava;

  public isel.lae.li41n.mapper.CourseInternal mapTo(isel.lae.li41n.mapper.CourseExt);
    descriptor: (Lisel/lae/li41n/mapper/CourseExt;)Lisel/lae/li41n/mapper/CourseInternal;
    flags: (0x0001) ACC_PUBLIC
    Code:
      stack=6, locals=5, args_size=2
         0: aload_1
         1: invokevirtual #7                  // Method isel/lae/li41n/mapper/CourseExt.getName:()Ljava/lang/String;
         4: astore_2
         5: aload_1
         6: invokevirtual #13                 // Method isel/lae/li41n/mapper/CourseExt.getSemester:()I
         9: istore_3
        10: aload_1
        11: invokevirtual #17                 // Method isel/lae/li41n/mapper/CourseExt.getProgramme:()Ljava/lang/String;
        14: astore        4
        16: new           #20                 // class isel/lae/li41n/mapper/CourseInternal
        19: dup
        20: aload_2
        21: iload_3
        22: aload         4
        24: iconst_m1
        25: invokespecial #22                 // Method isel/lae/li41n/mapper/CourseInternal."<init>":(Ljava/lang/String;ILjava/lang/String;I)V
        28: areturn
      LineNumberTable:
        line 9: 0
        line 10: 5
        line 11: 10
        line 13: 16
      LocalVariableTable:
        Start  Length  Slot  Name   Signature
            0      29     0  this   Lisel/lae/li41n/mapper/MapperDynCourseExtToCourseInternalJava;
            0      29     1   src   Lisel/lae/li41n/mapper/CourseExt;
            5      24     2  name   Ljava/lang/String;
           10      19     3 semester   I
           16      13     4 programme   Ljava/lang/String;

  public java.lang.Object mapTo(java.lang.Object);
    descriptor: (Ljava/lang/Object;)Ljava/lang/Object;
    flags: (0x1041) ACC_PUBLIC, ACC_BRIDGE, ACC_SYNTHETIC
    Code:
      stack=2, locals=2, args_size=2
         0: aload_0
         1: aload_1
         2: checkcast     #8                  // class isel/lae/li41n/mapper/CourseExt
         5: invokevirtual #25                 // Method mapTo:(Lisel/lae/li41n/mapper/CourseExt;)Lisel/lae/li41n/mapper/CourseInternal;
         8: areturn
      LineNumberTable:
        line 3: 0
      LocalVariableTable:
        Start  Length  Slot  Name   Signature
            0       9     0  this   Lisel/lae/li41n/mapper/MapperDynCourseExtToCourseInternalJava;
    MethodParameters:
      Name                           Flags
      <no name>                      synthetic
}
Signature: #48                          // Ljava/lang/Object;Lisel/lae/li41n/mapper/Mapper<Lisel/lae/li41n/mapper/CourseExt;Lisel/lae/li41n/mapper/CourseInternal;>;
SourceFile: "MapperDynCourseExtToCourseInternalJava.java"
