Classfile /Users/luisfalcao/Library/CloudStorage/OneDrive-InstitutoSuperiordeEngenhariadeLisboa/ISEL/Disciplinas/2024_2025/2024-2025VerLAE/Repositories/2025-lae-41n-LF/Lesson17/build/classes/kotlin/test/isel/lae/li41n/mapper/mappers/MapperDynCourseExtWithTeacherToCourseInternalWithTeacher.class
  Last modified Apr 27, 2025; size 2730 bytes
  SHA-256 checksum ff237e49680d5418eecc1bc3111469b1c24d54448078c22250ed7bb275ff0635
  Compiled from "MapperDynCourseExtWithTeacherToCourseInternalWithTeacher.kt"
public final class isel.lae.li41n.mapper.mappers.MapperDynCourseExtWithTeacherToCourseInternalWithTeacher extends java.lang.Object implements isel.lae.li41n.mapper.Mapper<isel.lae.li41n.mapper.domain.CourseExternalWithTeacher, isel.lae.li41n.mapper.domain.CourseInternalWithTeacher>
  minor version: 0
  major version: 66
  flags: (0x0031) ACC_PUBLIC, ACC_FINAL, ACC_SUPER
  this_class: #2                          // isel/lae/li41n/mapper/mappers/MapperDynCourseExtWithTeacherToCourseInternalWithTeacher
  super_class: #5                         // java/lang/Object
  interfaces: 1, fields: 1, methods: 3, attributes: 3
Constant pool:
   #1 = Utf8               isel/lae/li41n/mapper/mappers/MapperDynCourseExtWithTeacherToCourseInternalWithTeacher
   #2 = Class              #1             // isel/lae/li41n/mapper/mappers/MapperDynCourseExtWithTeacherToCourseInternalWithTeacher
   #3 = Utf8               Ljava/lang/Object;Lisel/lae/li41n/mapper/Mapper<Lisel/lae/li41n/mapper/domain/CourseExternalWithTeacher;Lisel/lae/li41n/mapper/domain/CourseInternalWithTeacher;>;
   #4 = Utf8               java/lang/Object
   #5 = Class              #4             // java/lang/Object
   #6 = Utf8               isel/lae/li41n/mapper/Mapper
   #7 = Class              #6             // isel/lae/li41n/mapper/Mapper
   #8 = Utf8               <init>
   #9 = Utf8               ()V
  #10 = NameAndType        #8:#9          // "<init>":()V
  #11 = Methodref          #5.#10         // java/lang/Object."<init>":()V
  #12 = Utf8               isel/lae/li41n/mapper/domain/TeacherExternal
  #13 = Class              #12            // isel/lae/li41n/mapper/domain/TeacherExternal
  #14 = Utf8               isel/lae/li41n/mapper/domain/TeacherInternal
  #15 = Class              #14            // isel/lae/li41n/mapper/domain/TeacherInternal
  #16 = Utf8               isel/lae/li41n/mapper/DynamicMapperKt
  #17 = Class              #16            // isel/lae/li41n/mapper/DynamicMapperKt
  #18 = Utf8               loadDynamicMapper
  #19 = Utf8               (Ljava/lang/Class;Ljava/lang/Class;)Lisel/lae/li41n/mapper/Mapper;
  #20 = NameAndType        #18:#19        // loadDynamicMapper:(Ljava/lang/Class;Ljava/lang/Class;)Lisel/lae/li41n/mapper/Mapper;
  #21 = Methodref          #17.#20        // isel/lae/li41n/mapper/DynamicMapperKt.loadDynamicMapper:(Ljava/lang/Class;Ljava/lang/Class;)Lisel/lae/li41n/mapper/Mapper;
  #22 = Utf8               teacherMapper
  #23 = Utf8               Lisel/lae/li41n/mapper/Mapper;
  #24 = NameAndType        #22:#23        // teacherMapper:Lisel/lae/li41n/mapper/Mapper;
  #25 = Fieldref           #2.#24         // isel/lae/li41n/mapper/mappers/MapperDynCourseExtWithTeacherToCourseInternalWithTeacher.teacherMapper:Lisel/lae/li41n/mapper/Mapper;
  #26 = Utf8               this
  #27 = Utf8               Lisel/lae/li41n/mapper/mappers/MapperDynCourseExtWithTeacherToCourseInternalWithTeacher;
  #28 = Utf8               mapTo
  #29 = Utf8               (Lisel/lae/li41n/mapper/domain/CourseExternalWithTeacher;)Lisel/lae/li41n/mapper/domain/CourseInternalWithTeacher;
  #30 = Utf8               Lorg/jetbrains/annotations/NotNull;
  #31 = Utf8               src
  #32 = String             #31            // src
  #33 = Utf8               kotlin/jvm/internal/Intrinsics
  #34 = Class              #33            // kotlin/jvm/internal/Intrinsics
  #35 = Utf8               checkNotNullParameter
  #36 = Utf8               (Ljava/lang/Object;Ljava/lang/String;)V
  #37 = NameAndType        #35:#36        // checkNotNullParameter:(Ljava/lang/Object;Ljava/lang/String;)V
  #38 = Methodref          #34.#37        // kotlin/jvm/internal/Intrinsics.checkNotNullParameter:(Ljava/lang/Object;Ljava/lang/String;)V
  #39 = Utf8               isel/lae/li41n/mapper/domain/CourseInternalWithTeacher
  #40 = Class              #39            // isel/lae/li41n/mapper/domain/CourseInternalWithTeacher
  #41 = Utf8               isel/lae/li41n/mapper/domain/CourseExternalWithTeacher
  #42 = Class              #41            // isel/lae/li41n/mapper/domain/CourseExternalWithTeacher
  #43 = Utf8               getName
  #44 = Utf8               ()Ljava/lang/String;
  #45 = NameAndType        #43:#44        // getName:()Ljava/lang/String;
  #46 = Methodref          #42.#45        // isel/lae/li41n/mapper/domain/CourseExternalWithTeacher.getName:()Ljava/lang/String;
  #47 = Utf8               getSemester
  #48 = Utf8               ()I
  #49 = NameAndType        #47:#48        // getSemester:()I
  #50 = Methodref          #42.#49        // isel/lae/li41n/mapper/domain/CourseExternalWithTeacher.getSemester:()I
  #51 = Utf8               getProgramme
  #52 = NameAndType        #51:#44        // getProgramme:()Ljava/lang/String;
  #53 = Methodref          #42.#52        // isel/lae/li41n/mapper/domain/CourseExternalWithTeacher.getProgramme:()Ljava/lang/String;
  #54 = Utf8               getTeacher
  #55 = Utf8               ()Lisel/lae/li41n/mapper/domain/TeacherExternal;
  #56 = NameAndType        #54:#55        // getTeacher:()Lisel/lae/li41n/mapper/domain/TeacherExternal;
  #57 = Methodref          #42.#56        // isel/lae/li41n/mapper/domain/CourseExternalWithTeacher.getTeacher:()Lisel/lae/li41n/mapper/domain/TeacherExternal;
  #58 = Utf8               (Ljava/lang/Object;)Ljava/lang/Object;
  #59 = NameAndType        #28:#58        // mapTo:(Ljava/lang/Object;)Ljava/lang/Object;
  #60 = InterfaceMethodref #7.#59         // isel/lae/li41n/mapper/Mapper.mapTo:(Ljava/lang/Object;)Ljava/lang/Object;
  #61 = Utf8               (Ljava/lang/String;ILjava/lang/String;Lisel/lae/li41n/mapper/domain/TeacherInternal;)V
  #62 = NameAndType        #8:#61         // "<init>":(Ljava/lang/String;ILjava/lang/String;Lisel/lae/li41n/mapper/domain/TeacherInternal;)V
  #63 = Methodref          #40.#62        // isel/lae/li41n/mapper/domain/CourseInternalWithTeacher."<init>":(Ljava/lang/String;ILjava/lang/String;Lisel/lae/li41n/mapper/domain/TeacherInternal;)V
  #64 = Utf8               Lisel/lae/li41n/mapper/domain/CourseExternalWithTeacher;
  #65 = NameAndType        #28:#29        // mapTo:(Lisel/lae/li41n/mapper/domain/CourseExternalWithTeacher;)Lisel/lae/li41n/mapper/domain/CourseInternalWithTeacher;
  #66 = Methodref          #2.#65         // isel/lae/li41n/mapper/mappers/MapperDynCourseExtWithTeacherToCourseInternalWithTeacher.mapTo:(Lisel/lae/li41n/mapper/domain/CourseExternalWithTeacher;)Lisel/lae/li41n/mapper/domain/CourseInternalWithTeacher;
  #67 = Utf8               Ljava/lang/Object;
  #68 = Utf8               Lisel/lae/li41n/mapper/Mapper<Lisel/lae/li41n/mapper/domain/TeacherExternal;Lisel/lae/li41n/mapper/domain/TeacherInternal;>;
  #69 = Utf8               Lkotlin/Metadata;
  #70 = Utf8               mv
  #71 = Integer            2
  #72 = Integer            1
  #73 = Integer            0
  #74 = Utf8               k
  #75 = Utf8               xi
  #76 = Integer            48
  #77 = Utf8               d1
  #78 = Utf8               \u0000 \n\u0002\u0018\u0002\n\u0002\u0018\u0002\n\u0002\u0018\u0002\n\u0002\u0018\u0002\n\u0002\b\u0003\n\u0002\u0018\u0002\n\u0002\u0018\u0002\n\u0002\b\u0003\u0018\u00002\u000e\u0012\u0004\u0012\u00020\u0002\u0012\u0004\u0012\u00020\u00030\u0001B\u0007¢\u0006\u0004\b\u0004\u0010\u0005J\u0010\u0010\t\u001a\u00020\u00032\u0006\u0010\n\u001a\u00020\u0002H\u0016R\u001a\u0010\u0006\u001a\u000e\u0012\u0004\u0012\u00020\u0007\u0012\u0004\u0012\u00020\b0\u0001X\u0082\u0004¢\u0006\u0002\n\u0000¨\u0006\u000b
  #79 = Utf8               d2
  #80 = Utf8               Lisel/lae/li41n/mapper/domain/CourseInternalWithTeacher;
  #81 = Utf8               Lisel/lae/li41n/mapper/domain/TeacherExternal;
  #82 = Utf8               Lisel/lae/li41n/mapper/domain/TeacherInternal;
  #83 = Utf8               Lesson17_test
  #84 = Utf8               MapperDynCourseExtWithTeacherToCourseInternalWithTeacher.kt
  #85 = Utf8               Signature
  #86 = Utf8               RuntimeInvisibleAnnotations
  #87 = Utf8               Code
  #88 = Utf8               LineNumberTable
  #89 = Utf8               LocalVariableTable
  #90 = Utf8               RuntimeInvisibleParameterAnnotations
  #91 = Utf8               SourceFile
  #92 = Utf8               RuntimeVisibleAnnotations
{
  private final isel.lae.li41n.mapper.Mapper<isel.lae.li41n.mapper.domain.TeacherExternal, isel.lae.li41n.mapper.domain.TeacherInternal> teacherMapper;
    descriptor: Lisel/lae/li41n/mapper/Mapper;
    flags: (0x0012) ACC_PRIVATE, ACC_FINAL
    Signature: #68                          // Lisel/lae/li41n/mapper/Mapper<Lisel/lae/li41n/mapper/domain/TeacherExternal;Lisel/lae/li41n/mapper/domain/TeacherInternal;>;
    RuntimeInvisibleAnnotations:
      0: #30()
        org.jetbrains.annotations.NotNull

  public isel.lae.li41n.mapper.mappers.MapperDynCourseExtWithTeacherToCourseInternalWithTeacher();
    descriptor: ()V
    flags: (0x0001) ACC_PUBLIC
    Code:
      stack=3, locals=1, args_size=1
         0: aload_0
         1: invokespecial #11                 // Method java/lang/Object."<init>":()V
         4: aload_0
         5: ldc           #13                 // class isel/lae/li41n/mapper/domain/TeacherExternal
         7: ldc           #15                 // class isel/lae/li41n/mapper/domain/TeacherInternal
         9: invokestatic  #21                 // Method isel/lae/li41n/mapper/DynamicMapperKt.loadDynamicMapper:(Ljava/lang/Class;Ljava/lang/Class;)Lisel/lae/li41n/mapper/Mapper;
        12: putfield      #25                 // Field teacherMapper:Lisel/lae/li41n/mapper/Mapper;
        15: return
      LineNumberTable:
        line 6: 0
        line 8: 4
        line 6: 15
      LocalVariableTable:
        Start  Length  Slot  Name   Signature
            0      16     0  this   Lisel/lae/li41n/mapper/mappers/MapperDynCourseExtWithTeacherToCourseInternalWithTeacher;

  public isel.lae.li41n.mapper.domain.CourseInternalWithTeacher mapTo(isel.lae.li41n.mapper.domain.CourseExternalWithTeacher);
    descriptor: (Lisel/lae/li41n/mapper/domain/CourseExternalWithTeacher;)Lisel/lae/li41n/mapper/domain/CourseInternalWithTeacher;
    flags: (0x0001) ACC_PUBLIC
    Code:
      stack=7, locals=2, args_size=2
         0: aload_1
         1: ldc           #32                 // String src
         3: invokestatic  #38                 // Method kotlin/jvm/internal/Intrinsics.checkNotNullParameter:(Ljava/lang/Object;Ljava/lang/String;)V
         6: new           #40                 // class isel/lae/li41n/mapper/domain/CourseInternalWithTeacher
         9: dup
        10: aload_1
        11: invokevirtual #46                 // Method isel/lae/li41n/mapper/domain/CourseExternalWithTeacher.getName:()Ljava/lang/String;
        14: aload_1
        15: invokevirtual #50                 // Method isel/lae/li41n/mapper/domain/CourseExternalWithTeacher.getSemester:()I
        18: aload_1
        19: invokevirtual #53                 // Method isel/lae/li41n/mapper/domain/CourseExternalWithTeacher.getProgramme:()Ljava/lang/String;
        22: aload_0
        23: getfield      #25                 // Field teacherMapper:Lisel/lae/li41n/mapper/Mapper;
        26: aload_1
        27: invokevirtual #57                 // Method isel/lae/li41n/mapper/domain/CourseExternalWithTeacher.getTeacher:()Lisel/lae/li41n/mapper/domain/TeacherExternal;
        30: invokeinterface #60,  2           // InterfaceMethod isel/lae/li41n/mapper/Mapper.mapTo:(Ljava/lang/Object;)Ljava/lang/Object;
        35: checkcast     #15                 // class isel/lae/li41n/mapper/domain/TeacherInternal
        38: invokespecial #63                 // Method isel/lae/li41n/mapper/domain/CourseInternalWithTeacher."<init>":(Ljava/lang/String;ILjava/lang/String;Lisel/lae/li41n/mapper/domain/TeacherInternal;)V
        41: areturn
      LineNumberTable:
        line 11: 6
        line 12: 10
        line 13: 14
        line 14: 18
        line 15: 22
        line 11: 38
      LocalVariableTable:
        Start  Length  Slot  Name   Signature
            0      42     0  this   Lisel/lae/li41n/mapper/mappers/MapperDynCourseExtWithTeacherToCourseInternalWithTeacher;
            0      42     1   src   Lisel/lae/li41n/mapper/domain/CourseExternalWithTeacher;
    RuntimeInvisibleAnnotations:
      0: #30()
        org.jetbrains.annotations.NotNull
    RuntimeInvisibleParameterAnnotations:
      parameter 0:
        0: #30()
          org.jetbrains.annotations.NotNull

  public java.lang.Object mapTo(java.lang.Object);
    descriptor: (Ljava/lang/Object;)Ljava/lang/Object;
    flags: (0x1041) ACC_PUBLIC, ACC_BRIDGE, ACC_SYNTHETIC
    Code:
      stack=2, locals=2, args_size=2
         0: aload_0
         1: aload_1
         2: checkcast     #42                 // class isel/lae/li41n/mapper/domain/CourseExternalWithTeacher
         5: invokevirtual #66                 // Method mapTo:(Lisel/lae/li41n/mapper/domain/CourseExternalWithTeacher;)Lisel/lae/li41n/mapper/domain/CourseInternalWithTeacher;
         8: areturn
      LineNumberTable:
        line 6: 0
      LocalVariableTable:
        Start  Length  Slot  Name   Signature
            0       9     0  this   Lisel/lae/li41n/mapper/mappers/MapperDynCourseExtWithTeacherToCourseInternalWithTeacher;
            0       9     1   src   Ljava/lang/Object;
}
Signature: #3                           // Ljava/lang/Object;Lisel/lae/li41n/mapper/Mapper<Lisel/lae/li41n/mapper/domain/CourseExternalWithTeacher;Lisel/lae/li41n/mapper/domain/CourseInternalWithTeacher;>;
SourceFile: "MapperDynCourseExtWithTeacherToCourseInternalWithTeacher.kt"
RuntimeVisibleAnnotations:
  0: #69(#70=[I#71,I#72,I#73],#74=I#72,#75=I#76,#77=[s#78],#79=[s#27,s#23,s#64,s#80,s#8,s#9,s#22,s#81,s#82,s#28,s#31,s#83])
    kotlin.Metadata(
      mv=[2,1,0]
      k=1
      xi=48
      d1=["\u0000 \n\u0002\u0018\u0002\n\u0002\u0018\u0002\n\u0002\u0018\u0002\n\u0002\u0018\u0002\n\u0002\b\u0003\n\u0002\u0018\u0002\n\u0002\u0018\u0002\n\u0002\b\u0003\u0018\u00002\u000e\u0012\u0004\u0012\u00020\u0002\u0012\u0004\u0012\u00020\u00030\u0001B\u0007¢\u0006\u0004\b\u0004\u0010\u0005J\u0010\u0010\t\u001a\u00020\u00032\u0006\u0010\n\u001a\u00020\u0002H\u0016R\u001a\u0010\u0006\u001a\u000e\u0012\u0004\u0012\u00020\u0007\u0012\u0004\u0012\u00020\b0\u0001X\u0082\u0004¢\u0006\u0002\n\u0000¨\u0006\u000b"]
      d2=["Lisel/lae/li41n/mapper/mappers/MapperDynCourseExtWithTeacherToCourseInternalWithTeacher;","Lisel/lae/li41n/mapper/Mapper;","Lisel/lae/li41n/mapper/domain/CourseExternalWithTeacher;","Lisel/lae/li41n/mapper/domain/CourseInternalWithTeacher;","<init>","()V","teacherMapper","Lisel/lae/li41n/mapper/domain/TeacherExternal;","Lisel/lae/li41n/mapper/domain/TeacherInternal;","mapTo","src","Lesson17_test"]
    )
